camog/__init__.py
camog/__init__.pyc
camog/_cfastcsv.so
camog/_csv.py
camog/_csv.pyc
camog/_version.py
camog-0.1.0.dist-info/DESCRIPTION.rst
camog-0.1.0.dist-info/METADATA
camog-0.1.0.dist-info/RECORD
camog-0.1.0.dist-info/WHEEL
camog-0.1.0.dist-info/metadata.json
camog-0.1.0.dist-info/top_level.txt
