Metadata-Version: 2.0
Name: camog
Version: 0.1.0
Summary: csv file reader
Home-page: https://github.com/walshb/camog
Author: Ben Walsh
Author-email: b@wumpster.com
License: Apache License 2.0
Keywords: csv reader
Platform: any
Classifier: Development Status :: 4 - Beta
Classifier: Intended Audience :: Developers
Classifier: License :: OSI Approved :: Apache Software License
Classifier: Programming Language :: Python
Classifier: Programming Language :: Python :: 2
Classifier: Programming Language :: Python :: 3
Classifier: Topic :: Software Development :: Libraries
Classifier: Topic :: Software Development :: Libraries :: Python Modules
